setup.py
ryans/__init__.py
ryans_891.egg-info/PKG-INFO
ryans_891.egg-info/SOURCES.txt
ryans_891.egg-info/dependency_links.txt
ryans_891.egg-info/requires.txt
ryans_891.egg-info/top_level.txt