Metadata-Version: 2.4
Name: ryans-891
Version: 0.0.1
Summary: Library Banner Khusus untuk Bot Discord Ryans
Author: Ryans
Classifier: Programming Language :: Python :: 3
Classifier: Operating System :: OS Independent
Requires-Dist: colorama
Dynamic: author
Dynamic: classifier
Dynamic: requires-dist
Dynamic: summary
